setup.py
ifs/__init__.py
ifs/cli.py
ifs/lib.py
ifs.egg-info/PKG-INFO
ifs.egg-info/SOURCES.txt
ifs.egg-info/dependency_links.txt
ifs.egg-info/entry_points.txt
ifs.egg-info/requires.txt
ifs.egg-info/top_level.txt
ifs/source/__init__.py
ifs/source/confd.py
ifs/source/consul-template.py
ifs/source/consul.py
ifs/source/docker.py
ifs/source/elasticsearch.py
ifs/source/envconsul.py
ifs/source/etcd.py
ifs/source/go.py
ifs/source/haproxy.py
ifs/source/hostess.py
ifs/source/influxdb.py
ifs/source/java8.py
ifs/source/jenkins.py
ifs/source/mongodb.py
ifs/source/nginx.py
ifs/source/nodejs.py
ifs/source/nomad.py
ifs/source/packer.py
ifs/source/percona-server.py
ifs/source/python2.py
ifs/source/python3.py
ifs/source/redis.py
ifs/source/rethinkdb.py
ifs/source/riak.py
ifs/source/template.py
ifs/source/terraform.py
ifs/source/tools.py
ifs/source/vagrant.py
ifs/source/vault.py
ifs/source/virtualbox.py