Metadata-Version: 1.0
Name: ifs
Version: 0.12.0
Summary: Install from source
Home-page: https://github.com/cbednarski/ifs
Author: Chris Bednarski
Author-email: banzaimonkey@gmail.com
License: ISC
Platform: UNKNOWN
